config/config-docker-falkordb-combined.yaml
config/config-docker-falkordb.yaml
config/config-docker-neo4j.yaml
config/config.yaml
config/mcp_config_stdio_example.json
src/__init__.py
src/graphiti_mcp_server.py
src/config/__init__.py
src/config/schema.py
src/models/__init__.py
src/models/entity_types.py
src/models/response_types.py
src/services/__init__.py
src/services/factories.py
src/services/queue_service.py
src/utils/__init__.py
src/utils/formatting.py
src/utils/utils.py
graphiti_mcp_varming-1.0.6.dist-info/METADATA
graphiti_mcp_varming-1.0.6.dist-info/WHEEL
graphiti_mcp_varming-1.0.6.dist-info/entry_points.txt
graphiti_mcp_varming-1.0.6.dist-info/RECORD
