Metadata-Version: 2.4
Name: graphiti-mcp-varming
Version: 1.0.6
Summary: Graphiti MCP Server - Enhanced fork with additional tools by Varming
Project-URL: Homepage, https://github.com/Varming73/graphiti
Project-URL: Repository, https://github.com/Varming73/graphiti
Project-URL: Issues, https://github.com/Varming73/graphiti/issues
Author-email: Varming <varming@example.com>
License: Apache-2.0
Keywords: ai,graphiti,knowledge-graph,llm,mcp
Classifier: Development Status :: 4 - Beta
Classifier: Intended Audience :: Developers
Classifier: License :: OSI Approved :: Apache Software License
Classifier: Programming Language :: Python :: 3
Classifier: Programming Language :: Python :: 3.10
Classifier: Programming Language :: Python :: 3.11
Classifier: Programming Language :: Python :: 3.12
Requires-Python: <4,>=3.10
Requires-Dist: graphiti-core-varming>=0.23.2
Requires-Dist: mcp>=1.21.0
Requires-Dist: openai>=1.91.0
Requires-Dist: pydantic-settings>=2.0.0
Requires-Dist: pyyaml>=6.0
Provides-Extra: all
Requires-Dist: anthropic>=0.49.0; extra == 'all'
Requires-Dist: azure-identity>=1.21.0; extra == 'all'
Requires-Dist: google-genai>=1.8.0; extra == 'all'
Requires-Dist: graphiti-core-varming[falkordb]>=0.23.1; extra == 'all'
Requires-Dist: groq>=0.2.0; extra == 'all'
Requires-Dist: sentence-transformers>=2.0.0; extra == 'all'
Requires-Dist: voyageai>=0.2.3; extra == 'all'
Provides-Extra: api-providers
Requires-Dist: anthropic>=0.49.0; extra == 'api-providers'
Requires-Dist: google-genai>=1.8.0; extra == 'api-providers'
Requires-Dist: groq>=0.2.0; extra == 'api-providers'
Requires-Dist: voyageai>=0.2.3; extra == 'api-providers'
Provides-Extra: azure
Requires-Dist: azure-identity>=1.21.0; extra == 'azure'
Provides-Extra: dev
Requires-Dist: graphiti-core-varming>=0.23.2; extra == 'dev'
Requires-Dist: httpx>=0.28.1; extra == 'dev'
Requires-Dist: mcp>=1.21.0; extra == 'dev'
Requires-Dist: pyright>=1.1.404; extra == 'dev'
Requires-Dist: pytest-asyncio>=0.21.0; extra == 'dev'
Requires-Dist: pytest>=8.0.0; extra == 'dev'
Requires-Dist: ruff>=0.7.1; extra == 'dev'
Provides-Extra: falkordb
Requires-Dist: graphiti-core-varming[falkordb]>=0.23.2; extra == 'falkordb'
Provides-Extra: providers
Requires-Dist: anthropic>=0.49.0; extra == 'providers'
Requires-Dist: google-genai>=1.8.0; extra == 'providers'
Requires-Dist: groq>=0.2.0; extra == 'providers'
Requires-Dist: sentence-transformers>=2.0.0; extra == 'providers'
Requires-Dist: voyageai>=0.2.3; extra == 'providers'
